{
  "tasks": [
    {
      "text": "nkhkjh",
      "day": "2021-08-27T07:59:30",
      "calorie": "86",
      "reminder": true,
      "id": 3
    },
    {
      "text": "sd",
      "day": "2021-08-27T08:17:31",
      "calorie": "23",
      "reminder": true,
      "id": 4
    },
    {
      "text": "qwwe",
      "day": "2021-08-27T10:45:16",
      "calorie": "213",
      "reminder": true,
      "id": 5
    },
    {
      "userId": "61289b2463a4eab41e043bd1",
      "text": "wqq",
      "day": "2021-08-27T10:50:36",
      "calorie": "211",
      "reminder": true,
      "id": 6
    }
  ],
  "users": {
    "email": "a@a.com",
    "password": "ojas"
  }
}